colcon_ros_cargo/__init__.py
colcon_ros_cargo/package_identification/__init__.py
colcon_ros_cargo/package_identification/ament_cargo.py
colcon_ros_cargo/task/__init__.py
colcon_ros_cargo/task/ament_cargo/__init__.py
colcon_ros_cargo/task/ament_cargo/build.py
colcon_ros_cargo/task/ament_cargo/test.py
colcon_ros_cargo-0.2.0.dist-info/METADATA
colcon_ros_cargo-0.2.0.dist-info/WHEEL
colcon_ros_cargo-0.2.0.dist-info/entry_points.txt
colcon_ros_cargo-0.2.0.dist-info/top_level.txt
colcon_ros_cargo-0.2.0.dist-info/zip-safe
colcon_ros_cargo-0.2.0.dist-info/RECORD
