Metadata-Version: 2.1
Name: colcon-ros-cargo
Version: 0.2.0
Summary: Extension for colcon to support Ament Cargo packages.
Home-page: https://colcon.readthedocs.io
Author: Nikolai Morin
Author-email: nnmmgit@gmail.com
Maintainer: Nikolai Morin
Maintainer-email: nnmmgit@gmail.com
License: Apache License, Version 2.0
Project-URL: Changelog, https://github.com/colcon/colcon-ros-cargo/milestones?state=closed
Project-URL: GitHub, https://github.com/colcon/colcon-ros-cargo/
Keywords: colcon
Classifier: Development Status :: 3 - Alpha
Classifier: Environment :: Plugins
Classifier: Intended Audience :: Developers
Classifier: License :: OSI Approved :: Apache Software License
Classifier: Operating System :: MacOS
Classifier: Operating System :: Microsoft :: Windows
Classifier: Operating System :: POSIX
Classifier: Programming Language :: Python
Classifier: Topic :: Software Development :: Build Tools
Requires-Dist: cargo-ament-build
Requires-Dist: colcon-core
Requires-Dist: colcon-library-path
Requires-Dist: colcon-cargo
Requires-Dist: colcon-ros
Requires-Dist: toml
Provides-Extra: test
Requires-Dist: flake8>=3.6.0; extra == "test"
Requires-Dist: flake8-blind-except; extra == "test"
Requires-Dist: flake8-builtins; extra == "test"
Requires-Dist: flake8-class-newline; extra == "test"
Requires-Dist: flake8-comprehensions; extra == "test"
Requires-Dist: flake8-deprecated; extra == "test"
Requires-Dist: flake8-docstrings; extra == "test"
Requires-Dist: flake8-import-order; extra == "test"
Requires-Dist: flake8-quotes; extra == "test"
Requires-Dist: pep8-naming; extra == "test"
Requires-Dist: pylint; extra == "test"
Requires-Dist: pytest; extra == "test"
Requires-Dist: pytest-cov; extra == "test"
Requires-Dist: scspell3k>=2.2; extra == "test"
